checkstat/__init__.py
checkstat/checkstat.py
checkstat/cli.py
checkstat-0.1.1.dist-info/entry_points.txt
checkstat-0.1.1.dist-info/WHEEL
checkstat-0.1.1.dist-info/METADATA
checkstat-0.1.1.dist-info/RECORD
