Metadata-Version: 2.1
Name: checkstat
Version: 0.1.1
Summary: 
Author: Franccesco Orozco
Author-email: franccesco@codingdose.info
Requires-Python: >=3.7,<4.0
Classifier: Programming Language :: Python :: 3
Classifier: Programming Language :: Python :: 3.7
Requires-Dist: click (>=7.0,<8.0)
Requires-Dist: colorama (>=0.4.1,<0.5.0)
Requires-Dist: requests (>=2.22,<3.0)
